xingyunlib/PIL_extend.py
xingyunlib/__init__.py
xingyunlib/all.py
xingyunlib/code.py
xingyunlib/color.py
xingyunlib/data.py
xingyunlib/dsfAdmin.py
xingyunlib/err.py
xingyunlib/http_spider.py
xingyunlib/image.py
xingyunlib/mail.py
xingyunlib/print_format.py
xingyunlib/pygame_extend.py
xingyunlib/render.py
xingyunlib/spell.py
xingyunlib/tkinter_extend.py
xingyunlib/updata_yourpackage.py
xingyunlib/user.py
xingyunlib/venv_install.py
xingyunlib/xesapi.py
xingyunlib/xesapp.py
xingyunlib/xesuser.py
xingyunlib-1.2.20210416.dist-info/METADATA
xingyunlib-1.2.20210416.dist-info/WHEEL
xingyunlib-1.2.20210416.dist-info/top_level.txt
xingyunlib-1.2.20210416.dist-info/RECORD
