Metadata-Version: 2.1
Name: xingyunlib
Version: 1.2.20210416
Summary: 星光☆学而思专用库
Home-page: UNKNOWN
Author: 严子昱
Author-email: yanziyu252625@qq.com
Maintainer: 严子昱
Maintainer-email: yanziyu252625@qq.com
License: BSD License
Platform: all
Classifier: Development Status :: 4 - Beta
Classifier: Operating System :: OS Independent
Classifier: Intended Audience :: Developers
Classifier: License :: OSI Approved :: BSD License
Classifier: Programming Language :: Python :: 3
Classifier: Topic :: Software Development :: Libraries
Requires-Dist: requests
Requires-Dist: pygame
Requires-Dist: zmail
Requires-Dist: pillow
Requires-Dist: numpy
